Metadata-Version: 2.1
Name: libdna
Version: 2.0.0
Summary: A library for working with DNA.
Home-page: https://github.com/antonybholmes/libdna
Author: Antony B Holmes
Author-email: antony.b.holmes@gmail.com
Classifier: Programming Language :: Python :: 3
Classifier: License :: OSI Approved :: MIT License
Classifier: Operating System :: OS Independent
License-File: LICENSE
